{
    "trials": [
        50,
        150,
        500,
        1000
    ],
    "autoschedule": [
        true,
        false
    ],
    "tuner": [
        "xgb_rank",
        "random"
    ],
    "model": {
        "resnet18": {
            "path": "dumps/onnx/frozen/resnet18-v1-7.onnx",
            "input_name": "data",
            "input_shape": [1, 3, 224, 224]
        },
        "resnet152": {
            "path": "dumps/onnx/frozen/resnet152-v1-7.onnx",
            "input_name": "data",
            "input_shape": [1, 3, 224, 224]
        },
        "densenet121": {
            "path": "dumps/onnx/frozen/densenet-9.onnx",
            "input_name": "data_0",
            "input_shape": [1, 3, 224, 224]
        },
        "yolov4": {
            "path": "dumps/onnx/frozen/yolov4.onnx",
            "input_name": "input_1:0",
            "input_shape": [1, 416, 416, 3]
        },
        "robertabase": {
            "path": "dumps/onnx/frozen/roberta-base-11.onnx",
            "input_name": "input_ids",
            "input_shape": [1, 512]
        }
    }
}